documark/.gitkeep
documark/__init__.py
documark/documentation.py
documark/inspection.py
documark/introspection.py
documark-0.8.0.dist-info/METADATA
documark-0.8.0.dist-info/WHEEL
documark-0.8.0.dist-info/licenses/LICENCE
documark-0.8.0.dist-info/RECORD
