Metadata-Version: 2.4
Name: documark
Version: 0.8.0
Summary: Markdown documentation for Python packages
Project-URL: Homepage, https://github.com/iris-solutions-team/documark
Project-URL: Documentation, https://iris-solutions-team.github.io/documark-pages
Project-URL: Bug Tracker, https://github.com/iris-solutions-team/documark/issues
Author-email: Jaromir Benes <jaromir.benes@gmail.com>
License-File: LICENCE
Keywords: documentation,markdown
Classifier: License :: OSI Approved :: MIT License
Classifier: Operating System :: OS Independent
Classifier: Programming Language :: Python :: 3
Requires-Python: >=3.12
